green_form/__init__.py
green_form-0.1.0.dist-info/METADATA
green_form-0.1.0.dist-info/WHEEL
green_form-0.1.0.dist-info/RECORD
