Metadata-Version: 2.1
Name: green-form
Version: 0.1.0
Summary: Give you the green form. A must have to get the 'Laisser-Passer A38'!
Author: Tom Gabrièle
Author-email: tgabriele@alwaysdata.com
Requires-Python: >=3.11,<4.0
Classifier: Programming Language :: Python :: 3
Classifier: Programming Language :: Python :: 3.11
